[
    {"bgmPlay":{"loop":1,"name":"eye01"}},
    {"bg_0f":{"layer":1,"filename":"eye01.bmp"}},
    {"crossfade":{"duration":1000}},
    {"waitTime":{"duration":2000}},
    {"bgColor":{"bgr":[0,0,0]}},
    {"crossfade":{"duration":2000}},
    {"bgmStop":{}},
    {"waitTime":{"duration":1000}},
    {"bg_10":{"layer":1,"filename":"bg21a.bmp"}},
    {"crossfade":{"duration":1000}},
    {"dialogVisible":{"visible":1}},
    {"bgmPlay":{"loop":1,"name":"bgm02"}},
    {"dialogIdx":{"idx":5410}},
    {"dialog":{"text":"AAAAAAAAAAAAAAAAAAAAAAA"},"__afterString":[0,0]},
    {"dialogIdx":{"idx":5411}},
    {"dialog":{"text":"AAAAAAAAAAAAAAA"},"__afterString":[0,0]},
    {"dialogIdx":{"idx":5412}},
    {"dialog":{"text":"AAAAAAAAAAAAAAAA"},"__afterString":[0,198,130,170]},
    {"dialogIdx":{"idx":5413}},
    {"dialog":{"text":"AAAAAAAAAAAAAAAAAAAAAAAAAAAAAA"},"__afterString":[0,0,0,0]},
    {"sePlay":{"idx":0,"loop":0,"name":"se085a"}},
    {"waitTime":{"duration":500}},
    {"dialogIdx":{"idx":5414}},
    {"dialog":{"text":"AAAAAAAAAAAAAAAAAAAAAAAAAAAA"},"__afterString":[0,0,0,0]},
    {"seStop":{"idx":0}},
    {"dialogIdx":{"idx":5415}},
    {"dialog":{"text":"AAAAAAAAAAAAAAAAAAAAAAAAAAAAAAAAAAAAAAAAAAAAAA"},"__afterString":[0,0,0,0]},
    {"dialogIdx":{"idx":5416}},
    {"dialog":{"text":"AAAAAAAAAAAAAAAAAAAAAAAAAAAAAAAAAAAAAA"},"__afterString":[0,66,0,0]},
    {"dialogIdx":{"idx":5417}},
    {"dialog":{"text":"AAAAAAAAAAAAAAAAAAAAAAAAAAAAAAAAAAAAAAAAAAAAAAAAAAAAAAAA"},"__afterString":[0,129,99]},
    {"dialogIdx":{"idx":5418}},
    {"dialog":{"text":"AAAAAAAAAAAAAAAAAAAAAAAAAAAAAAAAAAAAAAAAAAAAAAAAAAAAAA"},"__afterString":[0,0,129,99]},
    {"sePlay":{"idx":0,"loop":0,"name":"se085a"}},
    {"waitTime":{"duration":500}},
    {"dialogIdx":{"idx":5419}},
    {"dialog":{"text":"AAAAAAAAAAAAA"},"__afterString":[0,0]},
    {"seStop":{"idx":0}},
    {"dialogIdx":{"idx":5420}},
    {"dialog":{"text":"AAAAAAAAAAAAAAAAAAAAAAAAAAAAAA"},"__afterString":[0,0,0,0]},
    {"dialogIdx":{"idx":5421}},
    {"dialog":{"text":"AAAAAAAAAAAAAAAAA"},"__afterString":[0,240]},
    {"dialogIdx":{"idx":5422}},
    {"dialog":{"text":"AAAAAAAAAAAAAAAAAAAAAAAAAAAAAAAAAAAAAA"},"__afterString":[0,0,0,0]},
    {"dialogIdx":{"idx":5423}},
    {"dialog":{"text":"AAAAAAAAAAAAAAAAAAAAAAAAA"},"__afterString":[0,0]},
    {"dialogIdx":{"idx":5424}},
    {"dialog":{"text":"AAAAAA"},"__afterString":[0,226,178,0]},
    {"dialogIdx":{"idx":5425}},
    {"dialog":{"text":"AAAAAAAAAAAAAAAAAAAAAAAAAAA"},"__afterString":[0,0]},
    {"bgmStop":{}},
    {"sePlay":{"idx":0,"loop":0,"name":"se015a"}},
    {"waitTime":{"duration":1000}},
    {"dialogIdx":{"idx":5426}},
    {"dialog":{"text":"AAAAAAAAAAAAAAAAAAA"},"__afterString":[0,185]},
    {"dialogIdx":{"idx":5427}},
    {"dialog":{"text":"AAAAAAAAAAAAAAAAAAAAAAAA"},"__afterString":[0,0,0,0]},
    {"dialogVisible":{"visible":0}},
    {"sePlay":{"idx":0,"loop":0,"name":"se033a"}},
    {"bgColor":{"bgr":[0,0,0]}},
    {"crossfade":{"duration":500}},
    {"bg_0f":{"layer":1,"filename":"ev04b.bmp"}},
    {"crossfade":{"duration":1000}},
    {"dialogVisible":{"visible":1}},
    {"avatar":{"filename":"feri0317.png"},"__skipped":[[0]]},
    {"crossfade":{"duration":250}},
    {"dialog":{"text":"＃AAAA"},"__afterString":[0,226,178,0]},
    {"dialogIdx":{"idx":5428}},
    {"voPlay":{"name":"eri0754"}},
    {"dialog":{"text":"AAAAAAAAAAAAA"},"__afterString":[0,203]},
    {"avatar":{"filename":"fchi0102.png"},"__skipped":[[0]]},
    {"crossfade":{"duration":250}},
    {"dialog":{"text":"＃AAA"},"__afterString":[0,0]},
    {"dialogIdx":{"idx":5429}},
    {"voPlay":{"name":"chi0282"}},
    {"dialog":{"text":"AAAAAAAAAAAAAAAAAAAA"},"__afterString":[0,210,130,205]},
    {"avatar":{"filename":"feri0319.png"},"__skipped":[[0]]},
    {"crossfade":{"duration":250}},
    {"dialog":{"text":"＃AAAA"},"__afterString":[0,226,178,0]},
    {"dialogIdx":{"idx":5430}},
    {"voPlay":{"name":"eri0755"}},
    {"dialog":{"text":"AAAAAAAAAAAAAAAAAAAAAAAAAAAAAAAA"},"__afterString":[0,66,0,164]},
    {"avatar":{"filename":"fchi0105.png"},"__skipped":[[0]]},
    {"crossfade":{"duration":250}},
    {"dialog":{"text":"＃AAA"},"__afterString":[0,0]},
    {"dialogIdx":{"idx":5431}},
    {"voPlay":{"name":"chi0283"}},
    {"dialog":{"text":"AAAAAAAAAAAAAAAAAA"},"__afterString":[0,200,141,75]},
    {"fgClear":{}},
    {"crossfade":{"duration":250}},
    {"dialogIdx":{"idx":5432}},
    {"dialog":{"text":"AAAAAAAAAAAAAAAAAAAAAA"},"__afterString":[0,158,139,0]},
    {"sePlay":{"idx":0,"loop":0,"name":"se079a"}},
    {"dialogIdx":{"idx":5433}},
    {"dialog":{"text":"AAAAAAAAAAAAAAAAAAAAAAAAAAAA"},"__afterString":[0,0,0,0]},
    {"seStop":{"idx":0}},
    {"bg_10":{"layer":1,"filename":"bg21a.bmp"}},
    {"crossfade":{"duration":500}},
    {"bgmPlay":{"loop":1,"name":"bgm02"}},
    {"fg_12":{"layer":0,"filename":"seri0318.png"}},
    {"fgMetrics":{"layer":0,"scale":100,"xMid":640,"yTop":0}},
    {"crossfade":{"duration":500}},
    {"dialog":{"text":"＃AAAA"},"__afterString":[0,226,178,0]},
    {"dialogIdx":{"idx":5434}},
    {"voPlay":{"name":"eri0756"}},
    {"dialog":{"text":"AAAA"},"__afterString":[0,226,178,0]},
    {"fgClear":{}},
    {"fg_12":{"layer":0,"filename":"seri0318.png"}},
    {"fg_12":{"layer":1,"filename":"schi0106.png"}},
    {"fgMetrics":{"layer":0,"scale":100,"xMid":420,"yTop":0}},
    {"fgMetrics":{"layer":1,"scale":100,"xMid":860,"yTop":0}},
    {"crossfade":{"duration":500}},
    {"dialog":{"text":"＃AAA"},"__afterString":[0,0]},
    {"dialogIdx":{"idx":5435}},
    {"voPlay":{"name":"chi0284"}},
    {"dialog":{"text":"AAAAAAAA"},"__afterString":[0,118,0,185]},
    {"fg_12":{"layer":0,"filename":"seri0312.png"}},
    {"fgMetrics":{"layer":0,"scale":100,"xMid":420,"yTop":0}},
    {"fgMetrics":{"layer":1,"scale":100,"xMid":860,"yTop":0}},
    {"crossfade":{"duration":500}},
    {"dialog":{"text":"＃AAAA"},"__afterString":[0,226,178,0]},
    {"dialogIdx":{"idx":5436}},
    {"voPlay":{"name":"eri0757"}},
    {"dialog":{"text":"AAAAA"},"__afterString":[0,0]},
    {"fg_12":{"layer":1,"filename":"schi0307.png"}},
    {"fgMetrics":{"layer":0,"scale":100,"xMid":420,"yTop":0}},
    {"fgMetrics":{"layer":1,"scale":100,"xMid":860,"yTop":0}},
    {"crossfade":{"duration":500}},
    {"dialog":{"text":"＃AAA"},"__afterString":[0,0]},
    {"dialogIdx":{"idx":5437}},
    {"voPlay":{"name":"chi0285"}},
    {"dialog":{"text":"AAAAAAAAAAAAAAAAAAAAAAAAAAAAAAAAAAAAAA"},"__afterString":[0,66,0,0]},
    {"dialogIdx":{"idx":5438}},
    {"dialog":{"text":"AAAAAAAAAAAAAAAAAAAAAAAAAA"},"__afterString":[0,0,0,0]},
    {"fg_12":{"layer":0,"filename":"seri0403.png"}},
    {"fgMetrics":{"layer":0,"scale":100,"xMid":420,"yTop":0}},
    {"fgMetrics":{"layer":1,"scale":100,"xMid":860,"yTop":0}},
    {"crossfade":{"duration":500}},
    {"dialog":{"text":"＃AAAA"},"__afterString":[0,226,178,0]},
    {"dialogIdx":{"idx":5439}},
    {"voPlay":{"name":"eri0758"}},
    {"dialog":{"text":"AAAAAAAAAAA"},"__afterString":[0,187]},
    {"fg_12":{"layer":1,"filename":"schi0106.png"}},
    {"fgMetrics":{"layer":0,"scale":100,"xMid":420,"yTop":0}},
    {"fgMetrics":{"layer":1,"scale":100,"xMid":860,"yTop":0}},
    {"crossfade":{"duration":500}},
    {"dialog":{"text":"＃AAA"},"__afterString":[0,0]},
    {"dialogIdx":{"idx":5440}},
    {"voPlay":{"name":"chi0286"}},
    {"dialog":{"text":"AAAAAAAAAAAAAAAAAAAAAAAAAAAAAAAAAAAAAAAAAAAAAAAAAAAAA"},"__afterString":[0,66]},
    {"fg_12":{"layer":0,"filename":"seri0504.png"}},
    {"fgMetrics":{"layer":0,"scale":100,"xMid":420,"yTop":0}},
    {"fgMetrics":{"layer":1,"scale":100,"xMid":860,"yTop":0}},
    {"crossfade":{"duration":500}},
    {"dialog":{"text":"＃AAAA"},"__afterString":[0,226,178,0]},
    {"dialogIdx":{"idx":5441}},
    {"voPlay":{"name":"eri0759"}},
    {"dialog":{"text":"AAAAAAAAAAAAAAAAAAAAAAAAAAAAAAAAAAAAAAAAAAAAAAAA"},"__afterString":[0,196,130,189]},
    {"fg_12":{"layer":1,"filename":"schi0105.png"}},
    {"fgMetrics":{"layer":0,"scale":100,"xMid":420,"yTop":0}},
    {"fgMetrics":{"layer":1,"scale":100,"xMid":860,"yTop":0}},
    {"crossfade":{"duration":500}},
    {"dialog":{"text":"＃AAA"},"__afterString":[0,0]},
    {"dialogIdx":{"idx":5442}},
    {"voPlay":{"name":"chi0287"}},
    {"dialog":{"text":"AAAA"},"__afterString":[0,226,178,0]},
    {"fg_12":{"layer":0,"filename":"seri0505.png"}},
    {"fgMetrics":{"layer":0,"scale":100,"xMid":420,"yTop":0}},
    {"fgMetrics":{"layer":1,"scale":100,"xMid":860,"yTop":0}},
    {"crossfade":{"duration":500}},
    {"dialog":{"text":"＃AAAA"},"__afterString":[0,226,178,0]},
    {"dialogIdx":{"idx":5443}},
    {"voPlay":{"name":"eri0760"}},
    {"dialog":{"text":"AAAA"},"__afterString":[0,226,178,0]},
    {"fg_12":{"layer":1,"filename":"schi0106.png"}},
    {"fgMetrics":{"layer":0,"scale":100,"xMid":420,"yTop":0}},
    {"fgMetrics":{"layer":1,"scale":100,"xMid":860,"yTop":0}},
    {"crossfade":{"duration":500}},
    {"dialog":{"text":"＃AAA"},"__afterString":[0,0]},
    {"dialogIdx":{"idx":5444}},
    {"voPlay":{"name":"chi0288"}},
    {"dialog":{"text":"AAAAAAAAAAAAAAAAAAAA"},"__afterString":[0,164,130,169]},
    {"fg_12":{"layer":0,"filename":"seri0312.png"}},
    {"fgMetrics":{"layer":0,"scale":100,"xMid":420,"yTop":0}},
    {"fgMetrics":{"layer":1,"scale":100,"xMid":860,"yTop":0}},
    {"crossfade":{"duration":500}},
    {"dialog":{"text":"＃AAAA"},"__afterString":[0,226,178,0]},
    {"dialogIdx":{"idx":5445}},
    {"voPlay":{"name":"eri0761"}},
    {"dialog":{"text":"AAAAAA"},"__afterString":[0,226,178,0]},
    {"fgClear":{}},
    {"crossfade":{"duration":500}},
    {"dialogIdx":{"idx":5446}},
    {"dialog":{"text":"AAAAAAAAAAAAAAAAAAAA"},"__afterString":[0,164,130,169]},
    {"fgClear":{}},
    {"fg_12":{"layer":1,"filename":"schi0105.png"}},
    {"fgMetrics":{"layer":1,"scale":100,"xMid":640,"yTop":0}},
    {"crossfade":{"duration":500}},
    {"dialog":{"text":"＃AAA"},"__afterString":[0,0]},
    {"dialogIdx":{"idx":5447}},
    {"voPlay":{"name":"chi0289"}},
    {"dialog":{"text":"AAAAAA"},"__afterString":[0,226,178,0]},
    {"dialogIdx":{"idx":5448}},
    {"dialog":{"text":"AAAAAAAAAAAAAAAAAAAAA"},"__afterString":[0,169]},
    {"fgClear":{}},
    {"crossfade":{"duration":500}},
    {"dialogIdx":{"idx":5449}},
    {"dialog":{"text":"AAAAAAAAAAAAAAAAAAAAAAAAAAAAAAAAAAAAAAAA"},"__afterString":[0,0,0,0]},
    {"fgClear":{}},
    {"fg_12":{"layer":0,"filename":"seri0501.png"}},
    {"fgMetrics":{"layer":0,"scale":100,"xMid":640,"yTop":0}},
    {"crossfade":{"duration":500}},
    {"dialog":{"text":"＃AAAA"},"__afterString":[0,226,178,0]},
    {"dialogIdx":{"idx":5450}},
    {"voPlay":{"name":"eri0762"}},
    {"dialog":{"text":"AAAAAAAAAAAA"},"__afterString":[0,0,0,0]},
    {"fgClear":{}},
    {"crossfade":{"duration":500}},
    {"dialogIdx":{"idx":5451}},
    {"dialog":{"text":"AAAAAAAAAAAAA"},"__afterString":[0,0]},
    {"fgClear":{}},
    {"fg_12":{"layer":0,"filename":"seri0502.png"}},
    {"fgMetrics":{"layer":0,"scale":100,"xMid":640,"yTop":0}},
    {"crossfade":{"duration":500}},
    {"dialog":{"text":"＃AAAA"},"__afterString":[0,226,178,0]},
    {"dialogIdx":{"idx":5452}},
    {"voPlay":{"name":"eri0763"}},
    {"dialog":{"text":"AAAAAAAAAAAAAAA"},"__afterString":[0,0]},
    {"dialogIdx":{"idx":5453}},
    {"dialog":{"text":"AAAAAAAAA"},"__afterString":[0,200]},
    {"dialogVisible":{"visible":0}},
    {"bgmFadeOut":{"duration":1000}},
    {"bgColor":{"bgr":[0,0,0]}},
    {"crossfade":{"duration":1000}},
    {"bgmStop":{}},
    {"bg_10":{"layer":1,"filename":"bg13a.bmp"}},
    {"crossfade":{"duration":1000}},
    {"dialogVisible":{"visible":1}},
    {"dialogIdx":{"idx":5454}},
    {"dialog":{"text":"AAAAAAAAAA"},"__afterString":[0,233,129,118]},
    {"bgmPlay":{"loop":1,"name":"bgm01b"}},
    {"dialogIdx":{"idx":5455}},
    {"dialog":{"text":"AAAAAAAAAAAAAAAAAAAAAAAAAAAAAAAAA"},"__afterString":[0,196]},
    {"dialogIdx":{"idx":5456}},
    {"dialog":{"text":"AAAAAAAAAAAAAAAAAAAAAAAAAAAAAAAAAAAAAAAA"},"__afterString":[0,0,0,0]},
    {"fgClear":{}},
    {"fg_12":{"layer":1,"filename":"sner0408.png"}},
    {"fgMetrics":{"layer":1,"scale":100,"xMid":640,"yTop":0}},
    {"crossfade":{"duration":500}},
    {"dialog":{"text":"＃AAAA"},"__afterString":[0,226,178,0]},
    {"dialogIdx":{"idx":5457}},
    {"voPlay":{"name":"ner0020"}},
    {"dialog":{"text":"AAAAAAAAAAAAAAAAAAAAAAAAA"},"__afterString":[0,66]},
    {"fgClear":{}},
    {"fg_12":{"layer":0,"filename":"seri0304.png"}},
    {"fg_12":{"layer":1,"filename":"sner0408.png"}},
    {"fgMetrics":{"layer":0,"scale":100,"xMid":420,"yTop":0}},
    {"fgMetrics":{"layer":1,"scale":100,"xMid":860,"yTop":0}},
    {"crossfade":{"duration":500}},
    {"dialog":{"text":"＃AAAA"},"__afterString":[0,226,178,0]},
    {"dialogIdx":{"idx":5458}},
    {"voPlay":{"name":"eri0764"}},
    {"dialog":{"text":"AAAAAAAAAAAAAAA"},"__afterString":[0,0]},
    {"dialogIdx":{"idx":5459}},
    {"dialog":{"text":"AAAAAAAAAAAAAAAAAAAAAAA"},"__afterString":[0,0]},
    {"fg_12":{"layer":1,"filename":"sner0403.png"}},
    {"fgMetrics":{"layer":0,"scale":100,"xMid":420,"yTop":0}},
    {"fgMetrics":{"layer":1,"scale":100,"xMid":860,"yTop":0}},
    {"crossfade":{"duration":500}},
    {"dialog":{"text":"＃AAAA"},"__afterString":[0,226,178,0]},
    {"dialogIdx":{"idx":5460}},
    {"voPlay":{"name":"ner0021"}},
    {"dialog":{"text":"AAAAAAAAAAAAAAAAA"},"__afterString":[0,187]},
    {"dialogIdx":{"idx":5461}},
    {"dialog":{"text":"AAAAAAAAAAAAAAAAAAAAAAAAAAAAAAAAAAAAAAA"},"__afterString":[0,0]},
    {"dialogIdx":{"idx":5462}},
    {"dialog":{"text":"AAAAAAAAAAAAAAAAAA"},"__afterString":[0,170,140,169]},
    {"fg_12":{"layer":0,"filename":"seri0307.png"}},
    {"fgMetrics":{"layer":0,"scale":100,"xMid":420,"yTop":0}},
    {"fgMetrics":{"layer":1,"scale":100,"xMid":860,"yTop":0}},
    {"crossfade":{"duration":500}},
    {"dialog":{"text":"＃AAAA"},"__afterString":[0,226,178,0]},
    {"dialogIdx":{"idx":5463}},
    {"voPlay":{"name":"eri0765"}},
    {"dialog":{"text":"AAAAAAAAAAAAAAAA"},"__afterString":[0,198,129,65]},
    {"dialogIdx":{"idx":5464}},
    {"dialog":{"text":"AAAAAAAAAAAAAAAAAAAAAAAAAAAAAAAAA"},"__afterString":[0,233]},
    {"fg_12":{"layer":1,"filename":"sner0503.png"}},
    {"fgMetrics":{"layer":0,"scale":100,"xMid":420,"yTop":0}},
    {"fgMetrics":{"layer":1,"scale":100,"xMid":860,"yTop":0}},
    {"crossfade":{"duration":500}},
    {"dialog":{"text":"＃AAAA"},"__afterString":[0,226,178,0]},
    {"dialogIdx":{"idx":5465}},
    {"voPlay":{"name":"ner0022"}},
    {"dialog":{"text":"AAAAAAAAAAAAAAAAAAAAAAAAAAAAAAAA"},"__afterString":[0,66,0,241]},
    {"fg_12":{"layer":0,"filename":"seri0313.png"}},
    {"fgMetrics":{"layer":0,"scale":100,"xMid":420,"yTop":0}},
    {"fgMetrics":{"layer":1,"scale":100,"xMid":860,"yTop":0}},
    {"crossfade":{"duration":500}},
    {"dialog":{"text":"＃AAAA"},"__afterString":[0,226,178,0]},
    {"dialogIdx":{"idx":5466}},
    {"voPlay":{"name":"eri0766"}},
    {"dialog":{"text":"AAAAAAAAAAA"},"__afterString":[0,0]},
    {"fg_12":{"layer":1,"filename":"sner0403.png"}},
    {"fgMetrics":{"layer":0,"scale":100,"xMid":420,"yTop":0}},
    {"fgMetrics":{"layer":1,"scale":100,"xMid":860,"yTop":0}},
    {"crossfade":{"duration":500}},
    {"dialog":{"text":"＃AAAA"},"__afterString":[0,226,178,0]},
    {"dialogIdx":{"idx":5467}},
    {"voPlay":{"name":"ner0023"}},
    {"dialog":{"text":"AAAAAAAAAAAAAAAAAAAAA"},"__afterString":[0,165]},
    {"fgClear":{}},
    {"crossfade":{"duration":500}},
    {"dialogIdx":{"idx":5468}},
    {"dialog":{"text":"AAAAAAAAAAAAAAAAAAAAAAAAAAAAAAAAAAAA"},"__afterString":[0,196,129,118]},
    {"dialogIdx":{"idx":5469}},
    {"dialog":{"text":"AAAAAAAAAAAAAAAAAAAAA"},"__afterString":[0,65]},
    {"dialog":{"text":"＃AAAA"},"__afterString":[0,226,178,0]},
    {"dialogIdx":{"idx":5470}},
    {"voPlay":{"name":"rik0115"}},
    {"dialog":{"text":"AAAAAAAA"},"__afterString":[0,241,145,169]},
    {"dialogIdx":{"idx":5471}},
    {"dialog":{"text":"AAA"},"__afterString":[0,0]},
    {"fgClear":{}},
    {"fg_12":{"layer":1,"filename":"srik0801.png"}},
    {"fgMetrics":{"layer":1,"scale":100,"xMid":640,"yTop":0}},
    {"crossfade":{"duration":500}},
    {"dialogIdx":{"idx":5472}},
    {"dialog":{"text":"AAAAAAAAAAAAAAAAAAAAAAA"},"__afterString":[0,0]},
    {"fgClear":{}},
    {"fg_12":{"layer":1,"filename":"srik0801.png"}},
    {"fg_12":{"layer":2,"filename":"sner0401.png"}},
    {"fgMetrics":{"layer":1,"scale":100,"xMid":420,"yTop":0}},
    {"fgMetrics":{"layer":2,"scale":100,"xMid":860,"yTop":0}},
    {"crossfade":{"duration":500}},
    {"dialog":{"text":"＃AAAA"},"__afterString":[0,226,178,0]},
    {"dialogIdx":{"idx":5473}},
    {"voPlay":{"name":"ner0024"}},
    {"dialog":{"text":"AAAAAAAAAAAAAAAAAAAAAAAAAAAA"},"__afterString":[0,0,0,0]},
    {"fg_12":{"layer":1,"filename":"srik0820.png"}},
    {"fgMetrics":{"layer":1,"scale":100,"xMid":420,"yTop":0}},
    {"fgMetrics":{"layer":2,"scale":100,"xMid":860,"yTop":0}},
    {"crossfade":{"duration":500}},
    {"dialog":{"text":"＃AAA"},"__afterString":[0,0]},
    {"dialogIdx":{"idx":5474}},
    {"voPlay":{"name":"rik0116"}},
    {"dialog":{"text":"AAAAAAAA"},"__afterString":[0,119,130,181]},
    {"fg_12":{"layer":2,"filename":"sner0402.png"}},
    {"fgMetrics":{"layer":1,"scale":100,"xMid":420,"yTop":0}},
    {"fgMetrics":{"layer":2,"scale":100,"xMid":860,"yTop":0}},
    {"crossfade":{"duration":500}},
    {"dialog":{"text":"＃AAAA"},"__afterString":[0,226,178,0]},
    {"dialogIdx":{"idx":5475}},
    {"voPlay":{"name":"ner0025"}},
    {"dialog":{"text":"AAAAAAAAAAAAAAAAAAAAAAAAAAAAAAAAAAAAAAAA"},"__afterString":[0,196,130,162]},
    {"dialogIdx":{"idx":5476}},
    {"dialog":{"text":"AAAAAAAAAAAAAAAAAAAAAAAA"},"__afterString":[0,66,0,0]},
    {"fg_12":{"layer":1,"filename":"srik0811.png"}},
    {"fgMetrics":{"layer":1,"scale":100,"xMid":420,"yTop":0}},
    {"fgMetrics":{"layer":2,"scale":100,"xMid":860,"yTop":0}},
    {"crossfade":{"duration":500}},
    {"dialog":{"text":"＃AAA"},"__afterString":[0,0]},
    {"dialogIdx":{"idx":5477}},
    {"voPlay":{"name":"rik0117"}},
    {"dialog":{"text":"AAAAAA"},"__afterString":[0,226,178,0]},
    {"fgClear":{}},
    {"crossfade":{"duration":500}},
    {"dialogIdx":{"idx":5478}},
    {"dialog":{"text":"AAAAAAAAAAAAAAAAAA"},"__afterString":[0,237,130,175]},
    {"bgColor":{"bgr":[0,0,0]}},
    {"crossfade":{"duration":500}},
    {"waitTime":{"duration":2000}},
    {"bg_10":{"layer":1,"filename":"bg13a.bmp"}},
    {"crossfade":{"duration":1000}},
    {"fgClear":{}},
    {"fg_12":{"layer":1,"filename":"srik0914.png"}},
    {"fgMetrics":{"layer":1,"scale":100,"xMid":640,"yTop":0}},
    {"crossfade":{"duration":500}},
    {"dialog":{"text":"＃AAA"},"__afterString":[0,0]},
    {"dialogIdx":{"idx":5479}},
    {"voPlay":{"name":"rik0118"}},
    {"dialog":{"text":"AAAAAAAAAAAAAAAAA"},"__afterString":[0,66]},
    {"fgClear":{}},
    {"fg_12":{"layer":0,"filename":"seri0301.png"}},
    {"fg_12":{"layer":2,"filename":"srik0914.png"}},
    {"fgMetrics":{"layer":0,"scale":100,"xMid":420,"yTop":0}},
    {"fgMetrics":{"layer":2,"scale":100,"xMid":860,"yTop":0}},
    {"crossfade":{"duration":500}},
    {"dialog":{"text":"＃AAAA"},"__afterString":[0,226,178,0]},
    {"dialogIdx":{"idx":5480}},
    {"voPlay":{"name":"eri0767"}},
    {"dialog":{"text":"AAAAAAAAAAAAAAAAAAAAAAAAAAAAA"},"__afterString":[0,0]},
    {"fgClear":{}},
    {"fg_12":{"layer":2,"filename":"seri0301.png"}},
    {"fg_12":{"layer":0,"filename":"schi0101.png"}},
    {"fg_12":{"layer":1,"filename":"srik0914.png"}},
    {"fgMetrics":{"layer":2,"scale":100,"xMid":380,"yTop":0}},
    {"fgMetrics":{"layer":0,"scale":100,"xMid":640,"yTop":0}},
    {"fgMetrics":{"layer":1,"scale":100,"xMid":900,"yTop":0}},
    {"crossfade":{"duration":500}},
    {"dialog":{"text":"＃AAA"},"__afterString":[0,0]},
    {"dialogIdx":{"idx":5481}},
    {"voPlay":{"name":"chi0290"}},
    {"dialog":{"text":"AAAAAAAAAAAAAAAAAAAA"},"__afterString":[0,241,130,190]},
    {"dialogIdx":{"idx":5482}},
    {"dialog":{"text":"AAAAAAAAAAAAAAAAAAAAAAAAAAA"},"__afterString":[0,0]},
    {"fg_12":{"layer":1,"filename":"srik0901.png"}},
    {"fgMetrics":{"layer":2,"scale":100,"xMid":380,"yTop":0}},
    {"fgMetrics":{"layer":0,"scale":100,"xMid":640,"yTop":0}},
    {"fgMetrics":{"layer":1,"scale":100,"xMid":900,"yTop":0}},
    {"crossfade":{"duration":500}},
    {"dialog":{"text":"＃AAA"},"__afterString":[0,0]},
    {"dialogIdx":{"idx":5483}},
    {"voPlay":{"name":"rik0119"}},
    {"dialog":{"text":"AAAAAAAAAAAAAA"},"__afterString":[0,0,0,0]},
    {"fgClear":{}},
    {"crossfade":{"duration":500}},
    {"dialogIdx":{"idx":5484}},
    {"dialog":{"text":"AAAAAAAAAAAAA"},"__afterString":[0,118]},
    {"avatar":{"filename":"feri0404.png"},"__skipped":[[0]]},
    {"crossfade":{"duration":250}},
    {"dialog":{"text":"＃AAAA"},"__afterString":[0,226,178,0]},
    {"dialogIdx":{"idx":5485}},
    {"voPlay":{"name":"eri0768"}},
    {"dialog":{"text":"AAAAAAAAAAAAAAAA"},"__afterString":[0,198,141,162]},
    {"fgClear":{}},
    {"crossfade":{"duration":250}},
    {"dialogIdx":{"idx":5486}},
    {"dialog":{"text":"AAAAAAAAAAAAAAAAAAAAAAAAAAAAAAAAAAAAAAAA"},"__afterString":[0,0,0,0]},
    {"dialogIdx":{"idx":5487}},
    {"dialog":{"text":"AAAAAAAAAAAAAAAAAAAAAAAAAAAAAAAAAAAAAAAAAA"},"__afterString":[0,0,0,0]},
    {"dialogIdx":{"idx":5488}},
    {"dialog":{"text":"AAAAAAAAAAAAAAAAAAAAAAAAAAAAA"},"__afterString":[0,0]},
    {"fgClear":{}},
    {"fg_12":{"layer":0,"filename":"seri0312.png"}},
    {"fgMetrics":{"layer":0,"scale":100,"xMid":640,"yTop":0}},
    {"crossfade":{"duration":500}},
    {"dialog":{"text":"＃AAAA"},"__afterString":[0,226,178,0]},
    {"dialogIdx":{"idx":5489}},
    {"voPlay":{"name":"eri0769"}},
    {"dialog":{"text":"AAAAAAAAAAAAAAAAAAAAAAAAAAAAAAAAA"},"__afterString":[0,137]},
    {"fgClear":{}},
    {"fg_12":{"layer":0,"filename":"seri0312.png"}},
    {"fg_12":{"layer":2,"filename":"srik0913.png"}},
    {"fgMetrics":{"layer":0,"scale":100,"xMid":420,"yTop":0}},
    {"fgMetrics":{"layer":2,"scale":100,"xMid":860,"yTop":0}},
    {"crossfade":{"duration":500}},
    {"dialog":{"text":"＃AAA"},"__afterString":[0,0]},
    {"dialogIdx":{"idx":5490}},
    {"voPlay":{"name":"rik0120"}},
    {"dialog":{"text":"AAAAAAAAAAAAAAAAAAAAAAAAAAAAAAAAAAAAA"},"__afterString":[0,0]},
    {"fg_12":{"layer":0,"filename":"seri0508.png"}},
    {"fgMetrics":{"layer":0,"scale":100,"xMid":420,"yTop":0}},
    {"fgMetrics":{"layer":2,"scale":100,"xMid":860,"yTop":0}},
    {"crossfade":{"duration":500}},
    {"dialog":{"text":"＃AAAA"},"__afterString":[0,226,178,0]},
    {"dialogIdx":{"idx":5491}},
    {"voPlay":{"name":"eri0770"}},
    {"dialog":{"text":"AAAAAAAAAAAAAAAAAAAAAAAAAAAAAAAAAAAAAAAAAAAAAAAAAAAAAAA"},"__afterString":[0,99]},
    {"fg_12":{"layer":2,"filename":"srik0820.png"}},
    {"fgMetrics":{"layer":0,"scale":100,"xMid":420,"yTop":0}},
    {"fgMetrics":{"layer":2,"scale":100,"xMid":860,"yTop":0}},
    {"crossfade":{"duration":500}},
    {"dialog":{"text":"＃AAA"},"__afterString":[0,0]},
    {"dialogIdx":{"idx":5492}},
    {"voPlay":{"name":"rik0121"}},
    {"dialog":{"text":"AAAAAAA"},"__afterString":[0,0]},
    {"fg_12":{"layer":0,"filename":"seri0310.png"}},
    {"fgMetrics":{"layer":0,"scale":100,"xMid":420,"yTop":0}},
    {"fgMetrics":{"layer":2,"scale":100,"xMid":860,"yTop":0}},
    {"crossfade":{"duration":500}},
    {"dialog":{"text":"＃AAAA"},"__afterString":[0,226,178,0]},
    {"dialogIdx":{"idx":5493}},
    {"voPlay":{"name":"eri0771"}},
    {"dialog":{"text":"AAAAAAAAAAAAAAAAAAAAAAAAAAAAAAAAAAAAAAAAAAAAA"},"__afterString":[0,0]},
    {"fg_12":{"layer":2,"filename":"srik0813.png"}},
    {"fgMetrics":{"layer":0,"scale":100,"xMid":420,"yTop":0}},
    {"fgMetrics":{"layer":2,"scale":100,"xMid":860,"yTop":0}},
    {"crossfade":{"duration":500}},
    {"dialog":{"text":"＃AAA"},"__afterString":[0,0]},
    {"dialogIdx":{"idx":5494}},
    {"voPlay":{"name":"rik0122"}},
    {"dialog":{"text":"AAAAAAAAAAAAAAAAAAAAAAAAAAAAA"},"__afterString":[0,0]},
    {"fgClear":{}},
    {"crossfade":{"duration":500}},
    {"dialogIdx":{"idx":5495}},
    {"dialog":{"text":"AAAAAAAAAAAAAAAAAAAAAAAAAAA"},"__afterString":[0,237]},
    {"dialogIdx":{"idx":5496}},
    {"dialog":{"text":"AAAAAAAAAAAAAAAAAAAAAAAAAAAAAAAAAAAAAAA"},"__afterString":[0,0]},
    {"fgClear":{}},
    {"fg_12":{"layer":0,"filename":"seri0412.png"}},
    {"fgMetrics":{"layer":0,"scale":100,"xMid":640,"yTop":0}},
    {"crossfade":{"duration":500}},
    {"dialog":{"text":"＃AAAA"},"__afterString":[0,226,178,0]},
    {"dialogIdx":{"idx":5497}},
    {"voPlay":{"name":"eri0772"}},
    {"dialog":{"text":"AAAAAAAAAAAAAAAAAAAAAAAAAAAAAAAAAAAAAAAAAAAAAAA"},"__afterString":[0,0]},
    {"fgClear":{}},
    {"fg_12":{"layer":2,"filename":"seri0412.png"}},
    {"fg_12":{"layer":1,"filename":"schi0102.png"}},
    {"fgMetrics":{"layer":2,"scale":100,"xMid":420,"yTop":0}},
    {"fgMetrics":{"layer":1,"scale":100,"xMid":860,"yTop":0}},
    {"crossfade":{"duration":500}},
    {"dialog":{"text":"＃AAA"},"__afterString":[0,0]},
    {"dialogIdx":{"idx":5498}},
    {"voPlay":{"name":"chi0291"}},
    {"dialog":{"text":"AAAAA"},"__afterString":[0,0]},
    {"fgClear":{}},
    {"fg_12":{"layer":2,"filename":"seri0412.png"}},
    {"fg_12":{"layer":0,"filename":"schi0102.png"}},
    {"fg_12":{"layer":1,"filename":"srik0812.png"}},
    {"fgMetrics":{"layer":2,"scale":100,"xMid":380,"yTop":0}},
    {"fgMetrics":{"layer":0,"scale":100,"xMid":640,"yTop":0}},
    {"fgMetrics":{"layer":1,"scale":100,"xMid":900,"yTop":0}},
    {"crossfade":{"duration":500}},
    {"dialog":{"text":"＃AAA"},"__afterString":[0,0]},
    {"dialogIdx":{"idx":5499}},
    {"voPlay":{"name":"rik0123"}},
    {"dialog":{"text":"AAAAAAAAA"},"__afterString":[0,203]},
    {"fgClear":{}},
    {"crossfade":{"duration":500}},
    {"dialogIdx":{"idx":5500}},
    {"dialog":{"text":"AAAAAAAAAAAAAAAAAAAAAAAAAAAAAAAAAAAAAAAAAAAAAAAAAAAAAAA"},"__afterString":[0,99]},
    {"fgClear":{}},
    {"fg_12":{"layer":1,"filename":"schi0302.png"}},
    {"fgMetrics":{"layer":1,"scale":100,"xMid":640,"yTop":0}},
    {"crossfade":{"duration":500}},
    {"dialog":{"text":"＃AAA"},"__afterString":[0,0]},
    {"dialogIdx":{"idx":5501}},
    {"voPlay":{"name":"chi0292"}},
    {"dialog":{"text":"AAAAAAAAAAAAAAAAAAA"},"__afterString":[0,172]},
    {"fgClear":{}},
    {"crossfade":{"duration":500}},
    {"dialogIdx":{"idx":5502}},
    {"dialog":{"text":"AAAAAAAAAAAAAAAAAAAAAAA"},"__afterString":[0,0]},
    {"selBeg":{}},
    {"selAdd":{"text":"AAAAAAAAAAAAAAAAA","label":"label_0x2646"}},
    {"selAdd":{"text":"AAAAAAAAAAAAAA","label":"label_0x306e"}},
    {"selEnd":{"idx":15}},
"label_0x2646",
    {"varAdd":{"idx":100,"val":4}},
    {"varAdd":{"idx":108,"val":1}},
    {"yuri":{"action":2}},
    {"sePlay":{"idx":0,"loop":0,"name":"yuri_up"}},
    {"fgClear":{}},
    {"fg_12":{"layer":0,"filename":"seri0411.png"}},
    {"fgMetrics":{"layer":0,"scale":100,"xMid":640,"yTop":0}},
    {"crossfade":{"duration":500}},
    {"dialog":{"text":"＃AAAA"},"__afterString":[0,226,178,0]},
    {"dialogIdx":{"idx":5504}},
    {"voPlay":{"name":"eri0773"}},
    {"dialog":{"text":"AAAAAAAAAAAAAAAAAA"},"__afterString":[0,194,147,102]},
    {"fgClear":{}},
    {"fg_12":{"layer":0,"filename":"seri0411.png"}},
    {"fg_12":{"layer":1,"filename":"schi0303.png"}},
    {"fgMetrics":{"layer":0,"scale":100,"xMid":420,"yTop":0}},
    {"fgMetrics":{"layer":1,"scale":100,"xMid":860,"yTop":0}},
    {"crossfade":{"duration":500}},
    {"dialog":{"text":"＃AAA"},"__afterString":[0,0]},
    {"dialogIdx":{"idx":5505}},
    {"voPlay":{"name":"chi0293"}},
    {"dialog":{"text":"AAAAA"},"__afterString":[0,0]},
    {"fgClear":{}},
    {"crossfade":{"duration":500}},
    {"dialogIdx":{"idx":5506}},
    {"dialog":{"text":"AAAAAAAAAAAAAAAAAAAAAAAAAAAAAAAAAAAAAAAAA"},"__afterString":[0,245]},
    {"fgClear":{}},
    {"fg_12":{"layer":0,"filename":"seri0405.png"}},
    {"fgMetrics":{"layer":0,"scale":100,"xMid":640,"yTop":0}},
    {"crossfade":{"duration":500}},
    {"dialog":{"text":"＃AAAA"},"__afterString":[0,226,178,0]},
    {"dialogIdx":{"idx":5507}},
    {"voPlay":{"name":"eri0774"}},
    {"dialog":{"text":"AAAAAAAAAAAAAAAAAAAAAAAAAAAAAAAAAAAAAAAA"},"__afterString":[0,0,0,0]},
    {"fgClear":{}},
    {"fg_12":{"layer":1,"filename":"seri0405.png"}},
    {"fg_12":{"layer":0,"filename":"schi0101.png"}},
    {"fgMetrics":{"layer":1,"scale":100,"xMid":420,"yTop":0}},
    {"fgMetrics":{"layer":0,"scale":100,"xMid":860,"yTop":0}},
    {"crossfade":{"duration":500}},
    {"dialog":{"text":"＃AAA"},"__afterString":[0,0]},
    {"dialogIdx":{"idx":5508}},
    {"voPlay":{"name":"chi0294"}},
    {"dialog":{"text":"AAAAAAA"},"__afterString":[0,0]},
    {"fgClear":{}},
    {"fg_12":{"layer":3,"filename":"seri0405.png"}},
    {"fg_12":{"layer":1,"filename":"srik0819.png"}},
    {"fg_12":{"layer":0,"filename":"schi0101.png"}},
    {"fgMetrics":{"layer":3,"scale":100,"xMid":380,"yTop":0}},
    {"fgMetrics":{"layer":1,"scale":100,"xMid":640,"yTop":0}},
    {"fgMetrics":{"layer":0,"scale":100,"xMid":900,"yTop":0}},
    {"crossfade":{"duration":500}},
    {"dialog":{"text":"＃AAA"},"__afterString":[0,0]},
    {"dialogIdx":{"idx":5509}},
    {"voPlay":{"name":"rik0124"}},
    {"dialog":{"text":"AAAAAA"},"__afterString":[0,226,178,0]},
    {"fg_12":{"layer":3,"filename":"seri0309.png"}},
    {"fgMetrics":{"layer":3,"scale":100,"xMid":380,"yTop":0}},
    {"fgMetrics":{"layer":1,"scale":100,"xMid":640,"yTop":0}},
    {"fgMetrics":{"layer":0,"scale":100,"xMid":900,"yTop":0}},
    {"crossfade":{"duration":500}},
    {"dialog":{"text":"＃AAAA"},"__afterString":[0,226,178,0]},
    {"dialogIdx":{"idx":5510}},
    {"voPlay":{"name":"eri0775"}},
    {"dialog":{"text":"AAAAAAAAAAAAAAAAAAAAAAAAAAAAAAAAAAAAAAAAAAAAAAAAAAAA"},"__afterString":[0,189,130,230]},
    {"fg_12":{"layer":1,"filename":"srik0811.png"}},
    {"fgMetrics":{"layer":3,"scale":100,"xMid":380,"yTop":0}},
    {"fgMetrics":{"layer":1,"scale":100,"xMid":640,"yTop":0}},
    {"fgMetrics":{"layer":0,"scale":100,"xMid":900,"yTop":0}},
    {"crossfade":{"duration":500}},
    {"dialog":{"text":"＃AAA"},"__afterString":[0,0]},
    {"dialogIdx":{"idx":5511}},
    {"voPlay":{"name":"rik0125"}},
    {"dialog":{"text":"AAAAAAAAAAAAAAAAAAAAAAAAAAAAAAAAAAAAA"},"__afterString":[0,0]},
    {"fg_12":{"layer":0,"filename":"schi0303.png"}},
    {"fgMetrics":{"layer":3,"scale":100,"xMid":380,"yTop":0}},
    {"fgMetrics":{"layer":1,"scale":100,"xMid":640,"yTop":0}},
    {"fgMetrics":{"layer":0,"scale":100,"xMid":900,"yTop":0}},
    {"crossfade":{"duration":500}},
    {"dialog":{"text":"＃AAA"},"__afterString":[0,0]},
    {"dialogIdx":{"idx":5512}},
    {"voPlay":{"name":"chi0295"}},
    {"dialog":{"text":"AAAAAAAAAAAA"},"__afterString":[0,0,0,0]},
    {"fg_12":{"layer":3,"filename":"seri0405.png"}},
    {"fgMetrics":{"layer":3,"scale":100,"xMid":380,"yTop":0}},
    {"fgMetrics":{"layer":1,"scale":100,"xMid":640,"yTop":0}},
    {"fgMetrics":{"layer":0,"scale":100,"xMid":900,"yTop":0}},
    {"crossfade":{"duration":500}},
    {"dialog":{"text":"＃AAAA"},"__afterString":[0,226,178,0]},
    {"dialogIdx":{"idx":5513}},
    {"voPlay":{"name":"eri0776"}},
    {"dialog":{"text":"AAAAAAAAAAAAAAAAAAAAAAAAAAA"},"__afterString":[0,0]},
    {"fg_9c":{"layer":2,"filename":"srik0817.png"}},
    {"animOptA":{"layer":1,"xMid":640,"yTop":0,"xScale":100,"yScale":100,"alpha":255,"repeats":0},"__skipped":[[0,0],[0,90,0]]},
    {"animOptB":{"layer":1,"mode":1,"xMid":640,"yTop":0,"xScale":100,"yScale":100,"alpha":0,"duration":1}},
    {"animOptA":{"layer":3,"xMid":380,"yTop":0,"xScale":100,"yScale":100,"alpha":255,"repeats":0},"__skipped":[[0,0],[0,90,0]]},
    {"animOptB":{"layer":3,"mode":1,"xMid":380,"yTop":0,"xScale":100,"yScale":100,"alpha":255,"duration":1}},
    {"animOptA":{"layer":0,"xMid":900,"yTop":0,"xScale":100,"yScale":100,"alpha":255,"repeats":0},"__skipped":[[0,0],[0,90,0]]},
    {"animOptB":{"layer":0,"mode":1,"xMid":900,"yTop":0,"xScale":100,"yScale":100,"alpha":255,"duration":1}},
    {"animOptA":{"layer":2,"xMid":640,"yTop":0,"xScale":100,"yScale":100,"alpha":255,"repeats":0},"__skipped":[[0,0],[0,90,0]]},
    {"animOptB":{"layer":2,"mode":4,"xMid":640,"yTop":-16,"xScale":100,"yScale":100,"alpha":255,"duration":300}},
    {"animRunAll":{}},
    {"waitTime":{"duration":500}},
    {"animEnd_75":{"layer":0}},
    {"animEnd_75":{"layer":1}},
    {"animEnd_75":{"layer":2}},
    {"animEnd_75":{"layer":3}},
    {"dialog":{"text":"＃AAA"},"__afterString":[0,0]},
    {"dialogIdx":{"idx":5514}},
    {"voPlay":{"name":"rik0126"}},
    {"dialog":{"text":"AAAAAAA"},"__afterString":[0,0]},
    {"fgClear":{}},
    {"crossfade":{"duration":500}},
    {"dialogIdx":{"idx":5515}},
    {"dialog":{"text":"AAAAAAAAAAAAAAAAAAAAAAAAAAAAAAAAAAAAAAAAAAAA"},"__afterString":[0,0,0,0]},
    {"fgClear":{}},
    {"fg_12":{"layer":2,"filename":"srik0808.png"}},
    {"fgMetrics":{"layer":2,"scale":100,"xMid":640,"yTop":0}},
    {"crossfade":{"duration":500}},
    {"dialog":{"text":"＃AAA"},"__afterString":[0,0]},
    {"dialogIdx":{"idx":5516}},
    {"voPlay":{"name":"rik0127"}},
    {"dialog":{"text":"AAAAAAAAAAA"},"__afterString":[0,0]},
    {"dialogIdx":{"idx":5517}},
    {"dialog":{"text":"AAAAAAAAAAAAAAAAAAAAAAAAAAAAA"},"__afterString":[0,0]},
    {"fgClear":{}},
    {"fg_12":{"layer":0,"filename":"seri0310.png"}},
    {"fg_12":{"layer":2,"filename":"srik0808.png"}},
    {"fgMetrics":{"layer":0,"scale":100,"xMid":420,"yTop":0}},
    {"fgMetrics":{"layer":2,"scale":100,"xMid":860,"yTop":0}},
    {"crossfade":{"duration":500}},
    {"dialog":{"text":"＃AAAA"},"__afterString":[0,226,178,0]},
    {"dialogIdx":{"idx":5518}},
    {"voPlay":{"name":"eri0777"}},
    {"dialog":{"text":"AAAAAAAAAAAAAAAAAAAAAAAAAAAAAAAAAAAAA"},"__afterString":[0,118]},
    {"fg_12":{"layer":0,"filename":"seri0312.png"}},
    {"fgMetrics":{"layer":0,"scale":100,"xMid":420,"yTop":0}},
    {"fgMetrics":{"layer":2,"scale":100,"xMid":860,"yTop":0}},
    {"crossfade":{"duration":500}},
    {"dialog":{"text":"＃AAAA"},"__afterString":[0,226,178,0]},
    {"dialogIdx":{"idx":5519}},
    {"voPlay":{"name":"eri0778"}},
    {"dialog":{"text":"AAAAAAAAAAAAAAAAAAAAAAAAAAAAAAAAAA"},"__afterString":[0,224,129,65]},
    {"fg_12":{"layer":2,"filename":"srik0820.png"}},
    {"fgMetrics":{"layer":0,"scale":100,"xMid":420,"yTop":0}},
    {"fgMetrics":{"layer":2,"scale":100,"xMid":860,"yTop":0}},
    {"crossfade":{"duration":500}},
    {"dialog":{"text":"＃AAA"},"__afterString":[0,0]},
    {"dialogIdx":{"idx":5520}},
    {"voPlay":{"name":"rik0128"}},
    {"dialog":{"text":"AAAAA"},"__afterString":[0,0]},
    {"fg_12":{"layer":0,"filename":"seri0304.png"}},
    {"fgMetrics":{"layer":0,"scale":100,"xMid":420,"yTop":0}},
    {"fgMetrics":{"layer":2,"scale":100,"xMid":860,"yTop":0}},
    {"crossfade":{"duration":500}},
    {"dialog":{"text":"＃AAAA"},"__afterString":[0,226,178,0]},
    {"dialogIdx":{"idx":5521}},
    {"voPlay":{"name":"eri0779"}},
    {"dialog":{"text":"AAAAAAAAAAAAAAAAAAAAAAAAAAAAAAAAAAAAAAAAAAA"},"__afterString":[0,0]},
    {"jump":{"label":"label_0x3865"}},
"label_0x306e",
    {"varAdd":{"idx":100,"val":0}},
    {"varAdd":{"idx":108,"val":-1}},
    {"yuri":{"action":1}},
    {"sePlay":{"idx":0,"loop":0,"name":"yuri_down"}},
    {"dialogIdx":{"idx":5522}},
    {"dialog":{"text":"AAAAAAAAAAAAAAAAAAAAAAAAAAAAAAAA"},"__afterString":[0,85,130,193]},
    {"fgClear":{}},
    {"fg_12":{"layer":0,"filename":"seri0312.png"}},
    {"fgMetrics":{"layer":0,"scale":100,"xMid":640,"yTop":0}},
    {"crossfade":{"duration":500}},
    {"dialog":{"text":"＃AAAA"},"__afterString":[0,226,178,0]},
    {"dialogIdx":{"idx":5523}},
    {"voPlay":{"name":"eri0780"}},
    {"dialog":{"text":"AAAAAAAAAAAAAAAAAAAAAAAAAAAAAAAAAAAAAAAAAAAAAAAAAAAA"},"__afterString":[0,193,130,196]},
    {"fgClear":{}},
    {"fg_12":{"layer":0,"filename":"seri0312.png"}},
    {"fg_12":{"layer":2,"filename":"srik0914.png"}},
    {"fgMetrics":{"layer":0,"scale":100,"xMid":420,"yTop":0}},
    {"fgMetrics":{"layer":2,"scale":100,"xMid":860,"yTop":0}},
    {"crossfade":{"duration":500}},
    {"dialog":{"text":"＃AAA"},"__afterString":[0,0]},
    {"dialogIdx":{"idx":5524}},
    {"voPlay":{"name":"rik0129"}},
    {"dialog":{"text":"AAAAAAA"},"__afterString":[0,0]},
    {"fgClear":{}},
    {"crossfade":{"duration":500}},
    {"dialogIdx":{"idx":5525}},
    {"dialog":{"text":"AAAAAAAAAAAAAAAAAAAAAAAAAAAAAA"},"__afterString":[0,0,0,0]},
    {"dialogIdx":{"idx":5526}},
    {"dialog":{"text":"AAAAAAAAAAAAAAAAAAAAAAAA"},"__afterString":[0,240,140,169]},
    {"fgClear":{}},
    {"fg_12":{"layer":1,"filename":"schi0202.png"}},
    {"fgMetrics":{"layer":1,"scale":100,"xMid":640,"yTop":0}},
    {"crossfade":{"duration":500}},
    {"dialog":{"text":"＃AAA"},"__afterString":[0,0]},
    {"dialogIdx":{"idx":5527}},
    {"voPlay":{"name":"chi0296"}},
    {"dialog":{"text":"AAAAAAAAAAAAAAAAAA"},"__afterString":[0,110,141,108]},
    {"dialogIdx":{"idx":5528}},
    {"dialog":{"text":"AAAAAAAAAAAAA"},"__afterString":[0,0]},
    {"fgClear":{}},
    {"fg_12":{"layer":1,"filename":"schi0202.png"}},
    {"fg_12":{"layer":2,"filename":"srik0913.png"}},
    {"fgMetrics":{"layer":1,"scale":100,"xMid":420,"yTop":0}},
    {"fgMetrics":{"layer":2,"scale":100,"xMid":860,"yTop":0}},
    {"crossfade":{"duration":500}},
    {"dialog":{"text":"＃AAA"},"__afterString":[0,0]},
    {"dialogIdx":{"idx":5529}},
    {"voPlay":{"name":"rik0130"}},
    {"dialog":{"text":"AAAAAAAAAAAAAAAAAA"},"__afterString":[0,110,141,108]},
    {"fg_12":{"layer":1,"filename":"schi0303.png"}},
    {"fgMetrics":{"layer":1,"scale":100,"xMid":420,"yTop":0}},
    {"fgMetrics":{"layer":2,"scale":100,"xMid":860,"yTop":0}},
    {"crossfade":{"duration":500}},
    {"dialog":{"text":"＃AAA"},"__afterString":[0,0]},
    {"dialogIdx":{"idx":5530}},
    {"voPlay":{"name":"chi0297"}},
    {"dialog":{"text":"AAAAAAAAAAAAAAAAAAAAAAAAAAAAAAAAAAAAAA"},"__afterString":[0,66,0,0]},
    {"fgMetrics":{"layer":1,"scale":100,"xMid":420,"yTop":0}},
    {"fgMetrics":{"layer":2,"scale":100,"xMid":860,"yTop":0}},
    {"avatar":{"filename":"feri0403.png"},"__skipped":[[0]]},
    {"crossfade":{"duration":250}},
    {"dialog":{"text":"＃AAAA"},"__afterString":[0,226,178,0]},
    {"dialogIdx":{"idx":5531}},
    {"voPlay":{"name":"eri0781"}},
    {"dialog":{"text":"AAAAAA"},"__afterString":[0,226,178,0]},
    {"fgClear":{}},
    {"fg_12":{"layer":1,"filename":"schi0303.png"}},
    {"fg_12":{"layer":2,"filename":"srik0913.png"}},
    {"fgMetrics":{"layer":1,"scale":100,"xMid":420,"yTop":0}},
    {"fgMetrics":{"layer":2,"scale":100,"xMid":860,"yTop":0}},
    {"crossfade":{"duration":250}},
    {"dialogIdx":{"idx":5532}},
    {"dialog":{"text":"AAAAAAAAAAAAAAAAAAAAAAAAAAAAAAAAA"},"__afterString":[0,193]},
    {"fg_12":{"layer":2,"filename":"srik0822.png"}},
    {"fgMetrics":{"layer":1,"scale":100,"xMid":420,"yTop":0}},
    {"fgMetrics":{"layer":2,"scale":100,"xMid":860,"yTop":0}},
    {"crossfade":{"duration":500}},
    {"dialog":{"text":"＃AAA"},"__afterString":[0,0]},
    {"dialogIdx":{"idx":5533}},
    {"voPlay":{"name":"rik0131"}},
    {"dialog":{"text":"AAAAAAAAAAAAAAAA"},"__afterString":[0,190,130,193]},
    {"fgClear":{}},
    {"crossfade":{"duration":500}},
    {"dialogIdx":{"idx":5534}},
    {"dialog":{"text":"AAAAAAAAAAAAAAAAAAAAAAAAA"},"__afterString":[0,66]},
    {"dialogIdx":{"idx":5535}},
    {"dialog":{"text":"AAAAAAAAAAAAAAAAAAAAAAAAAAAAAAAAAAAAAAAAAAAAA"},"__afterString":[0,0]},
    {"fgClear":{}},
    {"fg_12":{"layer":0,"filename":"seri0304.png"}},
    {"fgMetrics":{"layer":0,"scale":100,"xMid":640,"yTop":0}},
    {"crossfade":{"duration":500}},
    {"dialog":{"text":"＃AAAA"},"__afterString":[0,226,178,0]},
    {"dialogIdx":{"idx":5536}},
    {"voPlay":{"name":"eri0782"}},
    {"dialog":{"text":"AAAAAAAAAAAAAAAAAAAAAAAAAAAAAAAAAAAAAAA"},"__afterString":[0,0]},
    {"fgClear":{}},
    {"fg_12":{"layer":0,"filename":"seri0304.png"}},
    {"fg_12":{"layer":2,"filename":"srik0802.png"}},
    {"fgMetrics":{"layer":0,"scale":100,"xMid":420,"yTop":0}},
    {"fgMetrics":{"layer":2,"scale":100,"xMid":860,"yTop":0}},
    {"crossfade":{"duration":500}},
    {"dialog":{"text":"＃AAA"},"__afterString":[0,0]},
    {"dialogIdx":{"idx":5537}},
    {"voPlay":{"name":"rik0132"}},
    {"dialog":{"text":"AAAAAAAAA"},"__afterString":[0,185]},
    {"fg_12":{"layer":0,"filename":"seri0307.png"}},
    {"fgMetrics":{"layer":0,"scale":100,"xMid":420,"yTop":0}},
    {"fgMetrics":{"layer":2,"scale":100,"xMid":860,"yTop":0}},
    {"crossfade":{"duration":500}},
    {"dialog":{"text":"＃AAAA"},"__afterString":[0,226,178,0]},
    {"dialogIdx":{"idx":5538}},
    {"voPlay":{"name":"eri0783"}},
    {"dialog":{"text":"AAAAAAAAAAAAAAAAAAAAAAAAAAAAAAAAAAAAA"},"__afterString":[0,0]},
    {"jump":{"label":"label_0x3865"}},
"label_0x3865",
    {"fg_12":{"layer":2,"filename":"srik0805.png"}},
    {"fgMetrics":{"layer":1,"scale":100,"xMid":420,"yTop":0}},
    {"fgMetrics":{"layer":2,"scale":100,"xMid":860,"yTop":0}},
    {"crossfade":{"duration":500}},
    {"dialog":{"text":"＃AAA"},"__afterString":[0,0]},
    {"dialogIdx":{"idx":5539}},
    {"voPlay":{"name":"rik0133"}},
    {"dialog":{"text":"AAAAAAAAAAAAAAAA"},"__afterString":[0,169,130,231]},
    {"fgClear":{}},
    {"fg_12":{"layer":2,"filename":"sner0503.png"}},
    {"fgMetrics":{"layer":2,"scale":100,"xMid":640,"yTop":0}},
    {"crossfade":{"duration":500}},
    {"dialog":{"text":"＃AAAA"},"__afterString":[0,226,178,0]},
    {"dialogIdx":{"idx":5540}},
    {"voPlay":{"name":"ner0026"}},
    {"dialog":{"text":"AAAAAAAAAAAAAAAA"},"__afterString":[0,169,130,231]},
    {"fgClear":{}},
    {"fg_12":{"layer":1,"filename":"srik0903.png"}},
    {"fg_12":{"layer":2,"filename":"sner0503.png"}},
    {"fgMetrics":{"layer":1,"scale":100,"xMid":420,"yTop":0}},
    {"fgMetrics":{"layer":2,"scale":100,"xMid":860,"yTop":0}},
    {"crossfade":{"duration":500}},
    {"dialog":{"text":"＃AAA"},"__afterString":[0,0]},
    {"dialogIdx":{"idx":5541}},
    {"voPlay":{"name":"rik0134"}},
    {"dialog":{"text":"AAAAAAAAA"},"__afterString":[0,233]},
    {"fg_12":{"layer":2,"filename":"sner0412.png"}},
    {"fgMetrics":{"layer":1,"scale":100,"xMid":420,"yTop":0}},
    {"fgMetrics":{"layer":2,"scale":100,"xMid":860,"yTop":0}},
    {"crossfade":{"duration":500}},
    {"dialog":{"text":"＃AAAA"},"__afterString":[0,226,178,0]},
    {"dialogIdx":{"idx":5542}},
    {"voPlay":{"name":"ner0027"}},
    {"dialog":{"text":"AAAAAAAAAAAAAAAAAAAA"},"__afterString":[0,220,130,189]},
    {"fg_12":{"layer":1,"filename":"srik0913.png"}},
    {"fgMetrics":{"layer":1,"scale":100,"xMid":420,"yTop":0}},
    {"fgMetrics":{"layer":2,"scale":100,"xMid":860,"yTop":0}},
    {"crossfade":{"duration":500}},
    {"dialog":{"text":"＃AAA"},"__afterString":[0,0]},
    {"dialogIdx":{"idx":5543}},
    {"voPlay":{"name":"rik0135"}},
    {"dialog":{"text":"AAAAAAA"},"__afterString":[0,0]},
    {"fg_12":{"layer":2,"filename":"sner0403.png"}},
    {"fgMetrics":{"layer":1,"scale":100,"xMid":420,"yTop":0}},
    {"fgMetrics":{"layer":2,"scale":100,"xMid":860,"yTop":0}},
    {"crossfade":{"duration":500}},
    {"dialog":{"text":"＃AAAA"},"__afterString":[0,226,178,0]},
    {"dialogIdx":{"idx":5544}},
    {"voPlay":{"name":"ner0028"}},
    {"dialog":{"text":"AAAAAAAAAAAAAAAAAAAAAAAAAAAAAAAAA"},"__afterString":[0,193]},
    {"fg_12":{"layer":1,"filename":"schi0102.png"}},
    {"fgMetrics":{"layer":1,"scale":100,"xMid":420,"yTop":0}},
    {"fgMetrics":{"layer":2,"scale":100,"xMid":860,"yTop":0}},
    {"crossfade":{"duration":500}},
    {"dialog":{"text":"＃AAA"},"__afterString":[0,0]},
    {"dialogIdx":{"idx":5545}},
    {"voPlay":{"name":"chi0298"}},
    {"dialog":{"text":"AAAAAAAAAAAAA"},"__afterString":[0,234]},
    {"fg_12":{"layer":2,"filename":"sner0510.png"}},
    {"fgMetrics":{"layer":1,"scale":100,"xMid":420,"yTop":0}},
    {"fgMetrics":{"layer":2,"scale":100,"xMid":860,"yTop":0}},
    {"crossfade":{"duration":500}},
    {"dialog":{"text":"＃AAAA"},"__afterString":[0,226,178,0]},
    {"dialogIdx":{"idx":5546}},
    {"voPlay":{"name":"ner0029"}},
    {"dialog":{"text":"AAAAA"},"__afterString":[0,0]},
    {"fg_12":{"layer":1,"filename":"schi0101.png"}},
    {"fgMetrics":{"layer":1,"scale":100,"xMid":420,"yTop":0}},
    {"fgMetrics":{"layer":2,"scale":100,"xMid":860,"yTop":0}},
    {"crossfade":{"duration":500}},
    {"dialog":{"text":"＃AAA"},"__afterString":[0,0]},
    {"dialogIdx":{"idx":5547}},
    {"voPlay":{"name":"chi0299"}},
    {"dialog":{"text":"AAAAAAAAAAAAAAAAAAA"},"__afterString":[0,165]},
    {"fgClear":{}},
    {"crossfade":{"duration":500}},
    {"dialogIdx":{"idx":5548}},
    {"dialog":{"text":"AAAAAAAAAAAAAAAAAAAAAAAAAAAA"},"__afterString":[0,0,0,0]},
    {"dialogIdx":{"idx":5549}},
    {"dialog":{"text":"AAAAAAAAAAAAAAAAAAAA"},"__afterString":[0,83,130,164]},
    {"fgClear":{}},
    {"fg_12":{"layer":2,"filename":"sner0401.png"}},
    {"fgMetrics":{"layer":2,"scale":100,"xMid":640,"yTop":0}},
    {"crossfade":{"duration":500}},
    {"dialog":{"text":"＃AAAA"},"__afterString":[0,226,178,0]},
    {"dialogIdx":{"idx":5550}},
    {"voPlay":{"name":"ner0030"}},
    {"dialog":{"text":"AAAAAAAAAAAAAAAAAAAAA"},"__afterString":[0,164]},
    {"fgClear":{}},
    {"crossfade":{"duration":500}},
    {"dialogIdx":{"idx":5551}},
    {"dialog":{"text":"AAAAAAAAAAAAAAAAAAAAAAAAAAAAAAAAAAAAAAAAAA"},"__afterString":[0,0,0,0]},
    {"dialogIdx":{"idx":5552}},
    {"dialog":{"text":"AAAAA"},"__afterString":[0,0]},
    {"bgmStop":{}},
    {"fgClear":{}},
    {"fg_12":{"layer":0,"filename":"seri0401.png"}},
    {"fgMetrics":{"layer":0,"scale":100,"xMid":640,"yTop":0}},
    {"crossfade":{"duration":500}},
    {"dialog":{"text":"＃AAAA"},"__afterString":[0,226,178,0]},
    {"dialogIdx":{"idx":5553}},
    {"voPlay":{"name":"eri0784"}},
    {"dialog":{"text":"AAAAAAAAAAA"},"__afterString":[0,0]},
    {"fgClear":{}},
    {"crossfade":{"duration":500}},
    {"dialogIdx":{"idx":5554}},
    {"dialog":{"text":"AAAAA"},"__afterString":[0,0]},
    {"dialogIdx":{"idx":5555}},
    {"dialog":{"text":"AAAAAAAAAAA"},"__afterString":[0,0]},
    {"fgClear":{}},
    {"fg_12":{"layer":0,"filename":"schi0102.png"}},
    {"fgMetrics":{"layer":0,"scale":100,"xMid":640,"yTop":0}},
    {"crossfade":{"duration":500}},
    {"dialog":{"text":"＃AAA"},"__afterString":[0,0]},
    {"dialogIdx":{"idx":5556}},
    {"voPlay":{"name":"chi0300"}},
    {"dialog":{"text":"AAAAAAAAAAAAAAAAAAAA"},"__afterString":[0,181,130,196]},
    {"dialogIdx":{"idx":5557}},
    {"dialog":{"text":"AAAAAAAAAAAAAAAAAAAAA"},"__afterString":[0,196]},
    {"fg_12":{"layer":0,"filename":"schi0303.png"}},
    {"fgMetrics":{"layer":0,"scale":100,"xMid":640,"yTop":0}},
    {"crossfade":{"duration":500}},
    {"dialog":{"text":"＃AAA"},"__afterString":[0,0]},
    {"dialogIdx":{"idx":5558}},
    {"voPlay":{"name":"chi0301"}},
    {"dialog":{"text":"AAAAAAAAAAAAA"},"__afterString":[0,0]},
    {"fgClear":{}},
    {"crossfade":{"duration":500}},
    {"dialogIdx":{"idx":5559}},
    {"dialog":{"text":"AAAAAAAAAAAAAAAAAAAAAAAAAAAAAAAAAAAAAAAAAAAAAAAAA"},"__afterString":[0,218]},
    {"fgClear":{}},
    {"fg_12":{"layer":0,"filename":"sner0402.png"}},
    {"fgMetrics":{"layer":0,"scale":100,"xMid":640,"yTop":0}},
    {"crossfade":{"duration":500}},
    {"dialog":{"text":"＃AAAA"},"__afterString":[0,226,178,0]},
    {"dialogIdx":{"idx":5560}},
    {"voPlay":{"name":"ner0031"}},
    {"dialog":{"text":"AAAAAAAAAAAAAAAAAAAAAAAAAAAA"},"__afterString":[0,0,0,0]},
    {"fgClear":{}},
    {"crossfade":{"duration":500}},
    {"dialogIdx":{"idx":5561}},
    {"dialog":{"text":"AAAAAAAAAAAAAAAAAAAAAAAAAAAAAAAAAAAAAAAAAAAAAAAAAAAAAAAAAAA"},"__afterString":[0,0]},
    {"dialogVisible":{"visible":0}},
    {"bgColor":{"bgr":[0,0,0]}},
    {"crossfade":{"duration":1000}},
    {"bgmPlay":{"loop":1,"name":"h_bgm10p"}},
    {"waitTime":{"duration":10000}},
    {"bgmFadeOut":{"duration":2000}},
    {"waitTime":{"duration":5000}},
    {"bgmStop":{}},
    {"dialogVisible":{"visible":1}},
    {"dialogIdx":{"idx":5562}},
    {"dialog":{"text":"AAAAAAAAA"},"__afterString":[0,66]},
    {"bg_10":{"layer":1,"filename":"bg21a.bmp"}},
    {"crossfade":{"duration":2000}},
    {"dialogIdx":{"idx":5563}},
    {"dialog":{"text":"AAAAAAAAAAAAAAAA"},"__afterString":[0,170,144,185]},
    {"dialogIdx":{"idx":5564}},
    {"dialog":{"text":"AAAAAAAAAAAAAAAAAAAAAAAAAAAAAAAAAAAAAAAAAA"},"__afterString":[0,0,0,0]},
    {"dialogIdx":{"idx":5565}},
    {"dialog":{"text":"AAAAAAAAAAAAAAAAAAAAAAAAAAAAAAAAAAAAAAAAAAAAAAAAAAA"},"__afterString":[0,204]},
    {"dialogIdx":{"idx":5566}},
    {"dialog":{"text":"AAAAAAAAAAAAAAAAAAAAAAAAAAAAAAAAAAAA"},"__afterString":[0,196,129,118]},
    {"dialogIdx":{"idx":5567}},
    {"dialog":{"text":"AAAAAAAAAAAAA"},"__afterString":[0,0]},
    {"dialogIdx":{"idx":5568}},
    {"dialog":{"text":"AAAAA"},"__afterString":[0,0]},
    {"dialogIdx":{"idx":5569}},
    {"dialog":{"text":"AAAAAAAAAAAAAAAAAAAAAAAAAAAAAAAAAAAAAAAAAAA"},"__afterString":[0,0]},
    {"dialogIdx":{"idx":5570}},
    {"voPlay":{"name":"ner0032"}},
    {"dialog":{"text":"AAAAAAAAAAAAAAAAAAA"},"__afterString":[0,65]},
    {"dialogIdx":{"idx":5571}},
    {"dialog":{"text":"AAAAAA"},"__afterString":[0,226,178,0]},
    {"dialogIdx":{"idx":5572}},
    {"dialog":{"text":"AAAAAAAAAAAAAAAAAAAAAAAAAA"},"__afterString":[0,0,0,0]},
    {"avatar":{"filename":"feri0820.png"},"__skipped":[[0]]},
    {"crossfade":{"duration":250}},
    {"dialog":{"text":"＃AAAA"},"__afterString":[0,226,178,0]},
    {"dialogIdx":{"idx":5573}},
    {"voPlay":{"name":"eri0785"}},
    {"dialog":{"text":"AAAAAAAAAAAAAAAAAA"},"__afterString":[0,66,129,144]},
    {"fgClear":{}},
    {"crossfade":{"duration":250}},
    {"dialogVisible":{"visible":0}},
    {"sePlay":{"idx":1,"loop":0,"name":"chi0001-03"}},
    {"waitTime":{"duration":5000}},
    {"dialogVisible":{"visible":1}},
    {"dialogIdx":{"idx":5574}},
    {"dialog":{"text":"AAAAAAAAAAAAAAAAAAAAAAAAAAAAAAAAAAAAAAAAAAA"},"__afterString":[0,0]},
    {"jumpEqual":{"idx":104,"val":1,"label":"label_0x45c8"}},
    {"jump":{"label":"label_0x4899"}},
"label_0x45c8",
    {"selBeg":{}},
    {"selAdd":{"text":"AAAAAAAAAAAAAAA","label":"label_0x460e"}},
    {"selAdd":{"text":"AAAAAAAA","label":"label_0x4899"}},
    {"selEnd":{"idx":52}},
"label_0x460e",
    {"dialogIdx":{"idx":5575}},
    {"dialog":{"text":"AAAAAAAAAAAAAAAAAAAAAAA"},"__afterString":[0,0]},
    {"varAdd":{"idx":104,"val":1}},
    {"sePlay":{"idx":0,"loop":0,"name":"se033a"}},
    {"waitTime":{"duration":1000}},
    {"dialogIdx":{"idx":5576}},
    {"dialog":{"text":"AAAAAAAAAAAAAAAAAAAAAAAAAAAAAAAAAAAAAA"},"__afterString":[0,66,0,0]},
    {"fgClear":{}},
    {"fg_12":{"layer":0,"filename":"seri0813.png"}},
    {"fgMetrics":{"layer":0,"scale":100,"xMid":640,"yTop":0}},
    {"crossfade":{"duration":500}},
    {"dialogIdx":{"idx":5577}},
    {"dialog":{"text":"AAAAAAAAA"},"__afterString":[0,231]},
    {"fgClear":{}},
    {"crossfade":{"duration":500}},
    {"sePlay":{"idx":0,"loop":0,"name":"se037a"}},
    {"waitTime":{"duration":1000}},
    {"dialogIdx":{"idx":5578}},
    {"dialog":{"text":"AAAAAAAAAAAAA"},"__afterString":[0,0]},
    {"dialogIdx":{"idx":5579}},
    {"dialog":{"text":"AAAAAAAAAAAAAAAAAAAAAAAAAA"},"__afterString":[0,0,0,0]},
    {"seStop":{"idx":0}},
    {"avatar":{"filename":"feri0801.png"},"__skipped":[[0]]},
    {"crossfade":{"duration":250}},
    {"dialog":{"text":"＃AAAA"},"__afterString":[0,226,178,0]},
    {"dialogIdx":{"idx":5580}},
    {"voPlay":{"name":"eri0786"}},
    {"dialog":{"text":"AAAAAAAAAAAAAAAAAAAAAAA"},"__afterString":[0,0]},
    {"fgClear":{}},
    {"crossfade":{"duration":250}},
    {"dialogIdx":{"idx":5581}},
    {"dialog":{"text":"AAAAA"},"__afterString":[0,0]},
    {"dialogIdx":{"idx":5582}},
    {"dialog":{"text":"AAAAAAAAAAAAAAAAAAAAAAAAAAAAAAAAA"},"__afterString":[0,205]},
    {"jump":{"label":"label_0x49b8"}},
    {"exit":{}},
"label_0x4899",
    {"dialogIdx":{"idx":5583}},
    {"dialog":{"text":"AAAAAAAAAAAAAAAAAA"},"__afterString":[0,187,130,193]},
    {"avatar":{"filename":"feri0821.png"},"__skipped":[[0]]},
    {"crossfade":{"duration":250}},
    {"dialog":{"text":"＃AAAA"},"__afterString":[0,226,178,0]},
    {"dialogIdx":{"idx":5584}},
    {"voPlay":{"name":"eri0787"}},
    {"dialog":{"text":"AAAAAAAAAAA"},"__afterString":[0,0]},
    {"fgClear":{}},
    {"crossfade":{"duration":250}},
    {"dialogIdx":{"idx":5585}},
    {"dialog":{"text":"AAAAAAAAAAAAAAAAAAAAAAAAAAAAAAAAAAAAAAAAAAAAAAAAAAAAAAAAA"},"__afterString":[0,77]},
"label_0x49b8",
    {"dialogVisible":{"visible":0}},
    {"seStop":{"idx":1}},
    {"bgColor":{"bgr":[0,0,0]}},
    {"crossfade":{"duration":3000}},
    {"waitTime":{"duration":2000}},
    {"jumpScript":{"filename":"02a_02300.s"}},
    {"exit":{}}
]